vid2ascii/__init__.py
vid2ascii/_util.py
vid2ascii/video.py
vid2ascii-0.3.1.dist-info/METADATA
vid2ascii-0.3.1.dist-info/WHEEL
vid2ascii-0.3.1.dist-info/licenses/LICENSE.txt
vid2ascii-0.3.1.dist-info/RECORD
